README.txt
setup.cfg
setup.py
SeoAnalyzer.egg-info/PKG-INFO
SeoAnalyzer.egg-info/SOURCES.txt
SeoAnalyzer.egg-info/dependency_links.txt
SeoAnalyzer.egg-info/not-zip-safe
SeoAnalyzer.egg-info/requires.txt
SeoAnalyzer.egg-info/top_level.txt
analyzer/__init__.py
analyzer/header.py