Metadata-Version: 1.0
Name: SeoAnalyzer
Version: 0.0.1
Summary: SEO Analysis Package
Home-page: http://bitbucket.org/whoosh/seo-analyzer
Author: Brian Bigelow
Author-email: brianb@whooshtraffic.com
License: PSF
Platform: UNKNOWN
Classifier: Intended Audience :: Developers
Classifier: License :: OSI Approved :: Python Software Foundation License
Classifier: Programming Language :: Python
Classifier: Topic :: Software Development :: Libraries :: Python Modules
